<?xml version="1.0" encoding="utf-8"?>
<!-- Created by ModBuddy on 5/4/2016 8:57:29 AM -->
<GameData>

	<!-- Pracinha now starts with Foreign Lands bonus. -->
	<Unit_FreePromotions>
		<Row>
			<UnitType>UNIT_BRAZILIAN_PRACINHA</UnitType>
			<PromotionType>PROMOTION_FOREIGN_LANDS</PromotionType>
		</Row>
	</Unit_FreePromotions>
	<Language_en_US>
		<Delete Tag="TXT_KEY_UNIT_HELP_BRAZILIAN_PRACINHA" />
		<Row Tag="TXT_KEY_UNIT_HELP_BRAZILIAN_PRACINHA">
			<Text>Modern Era infantry unit that earns points toward a [ICON_GOLDEN_AGE] Golden Age when it defeats an enemy and has a combat bonus outside of friendly territory. May only be built by Brazil.</Text>
		</Row>
	</Language_en_US>
	<Language_DE_DE>
		<Delete Tag="TXT_KEY_UNIT_HELP_BRAZILIAN_PRACINHA" />
		<Row Tag="TXT_KEY_UNIT_HELP_BRAZILIAN_PRACINHA">
			<Text>[COLOR_WARNING_TEXT](DE_DE text) [ENDCOLOR]Modern Era infantry unit that earns points toward a [ICON_GOLDEN_AGE] Golden Age when it defeats an enemy and has a combat bonus outside of friendly territory. May only be built by Brazil.</Text>
		</Row>
	</Language_DE_DE>
	<Language_PL_PL>
		<Delete Tag="TXT_KEY_UNIT_HELP_BRAZILIAN_PRACINHA" />
		<Row Tag="TXT_KEY_UNIT_HELP_BRAZILIAN_PRACINHA">
			<Text>[COLOR_WARNING_TEXT](PL_PL text) [ENDCOLOR]Modern Era infantry unit that earns points toward a [ICON_GOLDEN_AGE] Golden Age when it defeats an enemy and has a combat bonus outside of friendly territory. May only be built by Brazil.</Text>
		</Row>
	</Language_PL_PL>
	<Language_RU_RU>
		<Delete Tag="TXT_KEY_UNIT_HELP_BRAZILIAN_PRACINHA" />
		<Row Tag="TXT_KEY_UNIT_HELP_BRAZILIAN_PRACINHA">
			<Text>[COLOR_WARNING_TEXT](RU_RU text) [ENDCOLOR]Modern Era infantry unit that earns points toward a [ICON_GOLDEN_AGE] Golden Age when it defeats an enemy and has a combat bonus outside of friendly territory. May only be built by Brazil.</Text>
		</Row>
	</Language_RU_RU>

</GameData>