<?xml version="1.0" encoding="utf-8"?>
<!-- Created by ModBuddy on 2017-02-12 16:10:53 -->
<GameData>
	
	<!-- Party Leadership: +3 Happiness per City. -->
	<Policies>
		<Update>
			<Set Level="2" ExtraHappinessPerCity="3" />
			<Where Type="POLICY_PARTY_LEADERSHIP" />
		</Update>
	</Policies>
	<Policy_CityYieldChanges>
		<Delete PolicyType="POLICY_PARTY_LEADERSHIP" />
	</Policy_CityYieldChanges>

	<!-- localization -->
	<Language_en_US>
		<Delete Tag="TXT_KEY_POLICY_PARTY_LEADERSHIP_HELP" />
		<Row Tag="TXT_KEY_POLICY_PARTY_LEADERSHIP_HELP">
			<Text>[COLOR_POSITIVE_TEXT]Party Leadership[ENDCOLOR][NEWLINE]+3 [ICON_HAPPINESS_1] Happiness per City.</Text>
		</Row>
	</Language_en_US>
	<Language_DE_DE>
		<Delete Tag="TXT_KEY_POLICY_PARTY_LEADERSHIP_HELP" />
		<Row Tag="TXT_KEY_POLICY_PARTY_LEADERSHIP_HELP">
			<Text>[COLOR_WARNING_TEXT](DE_DE text) [ENDCOLOR][COLOR_POSITIVE_TEXT]Party Leadership[ENDCOLOR][NEWLINE]+3 [ICON_HAPPINESS_1] Happiness per City.</Text>
		</Row>
	</Language_DE_DE>
	<Language_PL_PL>
		<Delete Tag="TXT_KEY_POLICY_PARTY_LEADERSHIP_HELP" />
		<Row Tag="TXT_KEY_POLICY_PARTY_LEADERSHIP_HELP">
			<Text>[COLOR_WARNING_TEXT](PL_PL text) [ENDCOLOR][COLOR_POSITIVE_TEXT]Party Leadership[ENDCOLOR][NEWLINE]+3 [ICON_HAPPINESS_1] Happiness per City.</Text>
		</Row>
	</Language_PL_PL>
	<Language_RU_RU>
		<Delete Tag="TXT_KEY_POLICY_PARTY_LEADERSHIP_HELP" />
		<Row Tag="TXT_KEY_POLICY_PARTY_LEADERSHIP_HELP">
			<Text>[COLOR_WARNING_TEXT](RU_RU text) [ENDCOLOR][COLOR_POSITIVE_TEXT]Party Leadership[ENDCOLOR][NEWLINE]+3 [ICON_HAPPINESS_1] Happiness per City.</Text>
		</Row>
	</Language_RU_RU>

</GameData>